study_buddy/__init__.py
study_buddy/image.py
study_buddy/pdf.py
study_buddy/text.py
study_buddy-1.0.4.dist-info/METADATA
study_buddy-1.0.4.dist-info/WHEEL
study_buddy-1.0.4.dist-info/top_level.txt
study_buddy-1.0.4.dist-info/RECORD
